{"id":"8cfc61c9-7c42-4000-a6ae-6226d77fa000","priceOpen":49568.01,"position":"long","note":"","priceTakeProfit":51055.0503,"priceStopLoss":48576.6498,"minuteEstimatedTime":60,"symbol":"BTCUSDT","exchangeName":"binance_exchange","strategyName":"main_strategy","frameName":"feb_2024_frame","scheduledAt":1707892980000,"pendingAt":1707893040000,"_isScheduled":false,"originalPriceStopLoss":48576.6498,"originalPriceTakeProfit":51055.0503,"partialExecuted":0,"status":"closed","priority":1769445362861,"updatedAt":1707896640000,"pnl":{"pnlPercentage":2.8,"priceOpen":49568.01,"priceClose":50953.67},"createdAt":1707893040000}